mrbabel_data/__init__.py
mrbabel_data/_version.py
mrbabel_data/bart/ME-SE.cfl
mrbabel_data/bart/ME-SE.hdr
mrbabel_data/dicom/TE_20_SlcPos_-23.207628249046.dcm
mrbabel_data/dicom/TE_20_SlcPos_-33.707626341697.dcm
mrbabel_data/dicom/TE_40_SlcPos_-23.207628249046.dcm
mrbabel_data/dicom/TE_40_SlcPos_-33.707626341697.dcm
mrbabel_data/dicom/TE_60_SlcPos_-23.207628249046.dcm
mrbabel_data/dicom/TE_60_SlcPos_-33.707626341697.dcm
mrbabel_data/gehc/P20480_GRE.7
mrbabel_data/gehc/ScanArchive_GRE.h5
mrbabel_data/mrd/phantom.bin
mrbabel_data/mrd/spiral.h5
mrbabel_data/nifti/dicom_2D_16Echo_qT2_20101208191404_3_e1.json
mrbabel_data/nifti/dicom_2D_16Echo_qT2_20101208191404_3_e1.nii
mrbabel_data/nifti/dicom_2D_16Echo_qT2_20101208191404_3_e2.json
mrbabel_data/nifti/dicom_2D_16Echo_qT2_20101208191404_3_e2.nii
mrbabel_data/nifti/dicom_2D_16Echo_qT2_20101208191404_3_e3.json
mrbabel_data/nifti/dicom_2D_16Echo_qT2_20101208191404_3_e3.nii
mrbabel_data/siemens/gre.dat
mrbabel_data-1.0.1.dist-info/LICENSE.txt
mrbabel_data-1.0.1.dist-info/METADATA
mrbabel_data-1.0.1.dist-info/WHEEL
mrbabel_data-1.0.1.dist-info/top_level.txt
mrbabel_data-1.0.1.dist-info/RECORD
